girder_cli_oauth_client/__init__.py
girder_cli_oauth_client/client.py
girder_cli_oauth_client-0.4.0.dist-info/LICENSE
girder_cli_oauth_client-0.4.0.dist-info/METADATA
girder_cli_oauth_client-0.4.0.dist-info/WHEEL
girder_cli_oauth_client-0.4.0.dist-info/top_level.txt
girder_cli_oauth_client-0.4.0.dist-info/RECORD
