Metadata-Version: 2.1
Name: girder-cli-oauth-client
Version: 0.4.0
Summary: A Python library for performing OAuth login to a Girder 4 (Django) server.
Home-page: https://github.com/girder/girder-cli-oauth-client
Author: Kitware, Inc.
Author-email: kitware@kitware.com
License: Apache 2.0
Project-URL: Bug Reports, https://github.com/girder/girder-cli-oauth-client/issues
Project-URL: Source, https://github.com/girder/girder-cli-oauth-client
Platform: UNKNOWN
Classifier: Development Status :: 3 - Alpha
Classifier: Intended Audience :: Developers
Classifier: License :: OSI Approved :: Apache Software License
Classifier: Operating System :: OS Independent
Classifier: Programming Language :: Python :: 3
Classifier: Programming Language :: Python :: 3.8
Classifier: Programming Language :: Python
Requires-Python: >=3.8
License-File: LICENSE
Requires-Dist: authlib
Requires-Dist: pyxdg
Provides-Extra: dev
Requires-Dist: ipython ; extra == 'dev'
Requires-Dist: tox ; extra == 'dev'
Requires-Dist: click ; extra == 'dev'
Requires-Dist: requests ; extra == 'dev'
